fastapi_cloud/__about__.py
fastapi_cloud/__init__.py
fastapi_cloud-0.0.1.dist-info/METADATA
fastapi_cloud-0.0.1.dist-info/WHEEL
fastapi_cloud-0.0.1.dist-info/licenses/LICENSE.txt
fastapi_cloud-0.0.1.dist-info/RECORD
